Markdown2docx.py
PreprocessMarkdown2docx.py
Markdown2docx-0.0.1.dist-info/LICENCE
Markdown2docx-0.0.1.dist-info/METADATA
Markdown2docx-0.0.1.dist-info/WHEEL
Markdown2docx-0.0.1.dist-info/top_level.txt
Markdown2docx-0.0.1.dist-info/RECORD
