Metadata-Version: 2.1
Name: Markdown2docx
Version: 0.0.1
Summary: Convert Markdown to docx with token substitution and command output substitution
Home-page: UNKNOWN
Author: Jeremy Lee
Author-email: jlee2.71818@gmail.com
License: MIT
Keywords: convert,markdown,docx,merge,tokens,substitution,development
Platform: UNKNOWN
Classifier: Development Status :: 1 - Planning
Classifier: Intended Audience :: Science/Research
Classifier: License :: OSI Approved :: MIT License
Classifier: Programming Language :: Python :: 3
Classifier: Programming Language :: Python :: 3.6
Classifier: Programming Language :: Python :: 3.7
Classifier: Programming Language :: Python :: 3.8
Classifier: Programming Language :: Python :: 3.9
Classifier: Programming Language :: Python :: 3.10
Classifier: Operating System :: POSIX :: Linux
Classifier: Topic :: Text Processing :: Markup :: Markdown
Classifier: Topic :: Text Processing :: Markup :: reStructuredText
Classifier: Topic :: Documentation
License-File: LICENCE
Requires-Dist: bs4 (>=0.0.1)
Requires-Dist: pillow
Requires-Dist: python-docx (>=0.8.11)
Requires-Dist: markdown2 (>=2.4.2)
Provides-Extra: dev
Requires-Dist: pytest (>=3.7) ; extra == 'dev'
